haxor/__init__.py
haxor/__main__.py
haxor/command_line.py
haxor_game-0.0.15.dist-info/METADATA
haxor_game-0.0.15.dist-info/WHEEL
haxor_game-0.0.15.dist-info/top_level.txt
haxor_game-0.0.15.dist-info/RECORD
