Metadata-Version: 2.1
Name: haxor-game
Version: 0.0.15
Summary: How good are you at haxoring?
Home-page: https://github.com/adavila0703/haxor-game-python
Author: Angel Davila
Author-email: 
License: UNKNOWN
Platform: UNKNOWN
Classifier: Programming Language :: Python :: 3.8
Requires-Python: >=3.8
